netunicorn/director/infrastructure/connectors/__init__.py
netunicorn/director/infrastructure/connectors/salt_connector.py
netunicorn_connector_salt-0.3.8.dist-info/LICENSE
netunicorn_connector_salt-0.3.8.dist-info/METADATA
netunicorn_connector_salt-0.3.8.dist-info/WHEEL
netunicorn_connector_salt-0.3.8.dist-info/top_level.txt
netunicorn_connector_salt-0.3.8.dist-info/RECORD
