Metadata-Version: 2.1
Name: netunicorn-connector-salt
Version: 0.3.8
Summary: SaltStack connector for netunicorn
Author-email: Roman Beltiukov <rbeltiukov@ucsb.edu>
License: MIT
Keywords: netunicorn
Classifier: Programming Language :: Python :: 3
Requires-Python: >=3.10
License-File: LICENSE
Requires-Dist: netunicorn-base >=0.4.1
Requires-Dist: pyyaml
Requires-Dist: returns
Requires-Dist: aiohttp
